[
  {
    "anonymous": false,
    "inputs": [
      {
        "indexed": false,
        "internalType": "address",
        "name": "depositor",
        "type": "address"
      }
    ],
    "name": "DepositorSet",
    "type": "event"
  },
  {
    "anonymous": false,
    "inputs": [
      {
        "indexed": false,
        "internalType": "address",
        "name": "token0",
        "type": "address"
      },
      {
        "indexed": false,
        "internalType": "address",
        "name": "token1",
        "type": "address"
      },
      {
        "indexed": false,
        "internalType": "uint24",
        "name": "fee",
        "type": "uint24"
      },
      {
        "indexed": false,
        "internalType": "address",
        "name": "krystalVaultV3",
        "type": "address"
      },
      {
        "indexed": false,
        "internalType": "uint256",
        "name": "",
        "type": "uint256"
      }
    ],
    "name": "VaultCreated",
    "type": "event"
  },
  {
    "inputs": [],
    "name": "allVaultsLength",
    "outputs": [
      {
        "internalType": "uint256",
        "name": "",
        "type": "uint256"
      }
    ],
    "stateMutability": "view",
    "type": "function"
  },
  {
    "inputs": [
      {
        "internalType": "address",
        "name": "tokenA",
        "type": "address"
      },
      {
        "internalType": "address",
        "name": "tokenB",
        "type": "address"
      },
      {
        "internalType": "uint24",
        "name": "fee",
        "type": "uint24"
      },
      {
        "internalType": "string",
        "name": "name",
        "type": "string"
      },
      {
        "internalType": "string",
        "name": "symbol",
        "type": "string"
      }
    ],
    "name": "createVault",
    "outputs": [
      {
        "internalType": "address",
        "name": "krystalVaultV3",
        "type": "address"
      }
    ],
    "stateMutability": "nonpayable",
    "type": "function"
  },
  {
    "inputs": [
      {
        "internalType": "address",
        "name": "_depositor",
        "type": "address"
      }
    ],
    "name": "setDepositor",
    "outputs": [],
    "stateMutability": "nonpayable",
    "type": "function"
  }
]
